gundi_core/__init__.py
gundi_core/commands/__init__.py
gundi_core/commands/core.py
gundi_core/commands/integrations.py
gundi_core/events/__init__.py
gundi_core/events/core.py
gundi_core/events/dispatchers.py
gundi_core/events/gundi_api.py
gundi_core/events/gundi_configs.py
gundi_core/events/integrations.py
gundi_core/events/transformers.py
gundi_core/schemas/__init__.py
gundi_core/schemas/v1.py
gundi_core/schemas/v2/__init__.py
gundi_core/schemas/v2/earthranger.py
gundi_core/schemas/v2/gundi.py
gundi_core/schemas/v2/inreach.py
gundi_core/schemas/v2/smart.py
gundi_core/schemas/v2/traptagger.py
gundi_core/schemas/v2/wpswatch.py
gundi_core-1.11.2.dist-info/LICENSE
gundi_core-1.11.2.dist-info/METADATA
gundi_core-1.11.2.dist-info/WHEEL
gundi_core-1.11.2.dist-info/RECORD
